docdantic/__init__.py
docdantic/py.typed
docdantic-0.3.1.dist-info/LICENSE
docdantic-0.3.1.dist-info/METADATA
docdantic-0.3.1.dist-info/WHEEL
docdantic-0.3.1.dist-info/RECORD
