Metadata-Version: 2.1
Name: docdantic
Version: 0.3.1
Summary: A markdown plugin for generating docs from Pydantic models
Home-page: https://gitlab.com/emergentmethods/docdantic
License: MIT
Author: Tim Pogue
Author-email: tim@emergentmethods.ai
Requires-Python: >=3.11,<4.0
Classifier: License :: OSI Approved :: MIT License
Classifier: Programming Language :: Python :: 3
Classifier: Programming Language :: Python :: 3.11
Classifier: Programming Language :: Python :: 3.12
Requires-Dist: markdown (>=3.3.7,<4.0.0)
Requires-Dist: pydantic (>=2.5.0,<3.0.0)
Requires-Dist: tabulate (>=0.9.0,<0.10.0)
Project-URL: Repository, https://gitlab.com/emergentmethods/docdantic
